a_cv2_split_images_into_equal_parts/LICENSE
a_cv2_split_images_into_equal_parts/README.MD
a_cv2_split_images_into_equal_parts/__init__.py
a_cv2_split_images_into_equal_parts/requirements.txt
a_cv2_split_images_into_equal_parts/thirdparty.json
a_cv2_split_images_into_equal_parts-0.10.dist-info/LICENSE.rst
a_cv2_split_images_into_equal_parts-0.10.dist-info/METADATA
a_cv2_split_images_into_equal_parts-0.10.dist-info/WHEEL
a_cv2_split_images_into_equal_parts-0.10.dist-info/top_level.txt
a_cv2_split_images_into_equal_parts-0.10.dist-info/RECORD
